<activemq-journal>
   <bindings>
      <address-binding routing-types="ANYCAST" name="DLQ" id="2"/>
      <address-binding routing-types="MULTICAST" name="VirtualTopic" id="18"/>
      <address-binding routing-types="MULTICAST" name="activemq.notifications" id="20"/>
      <address-binding routing-types="ANYCAST" name="ExpiryQueue" id="6"/>
      <address-binding routing-types="ANYCAST" name="TEST.IN" id="10"/>
      <address-binding routing-types="ANYCAST" name="que1" id="58"/>
      <address-binding routing-types="ANYCAST" name="A.TEST.IN" id="14"/>
      <queue-binding address="A.TEST.IN" filter-string="" name="A.TEST.IN" id="16" routing-type="ANYCAST"/>
      <queue-binding address="DLQ" filter-string="" name="DLQ" id="4" routing-type="ANYCAST"/>
      <queue-binding address="ExpiryQueue" filter-string="" name="ExpiryQueue" id="8" routing-type="ANYCAST"/>
      <queue-binding address="que1" filter-string="" name="que1" id="56" routing-type="ANYCAST"/>
      <queue-binding address="TEST.IN" filter-string="" name="TEST.IN" id="12" routing-type="ANYCAST"/>
   </bindings>
</activemq-journal>
